odoo/addons/web_widget_google_marker_icon_picker/README.rst
odoo/addons/web_widget_google_marker_icon_picker/__init__.py
odoo/addons/web_widget_google_marker_icon_picker/__manifest__.py
odoo/addons/web_widget_google_marker_icon_picker/i18n/web_widget_google_marker_icon_picker.pot
odoo/addons/web_widget_google_marker_icon_picker/readme/CONTRIBUTORS.rst
odoo/addons/web_widget_google_marker_icon_picker/readme/DESCRIPTION.rst
odoo/addons/web_widget_google_marker_icon_picker/readme/USAGE.rst
odoo/addons/web_widget_google_marker_icon_picker/static/description/icon.png
odoo/addons/web_widget_google_marker_icon_picker/static/description/index.html
odoo/addons/web_widget_google_marker_icon_picker/static/description/widget_marker_picker.png
odoo/addons/web_widget_google_marker_icon_picker/static/src/img/markers/aqua.png
odoo/addons/web_widget_google_marker_icon_picker/static/src/img/markers/blue.png
odoo/addons/web_widget_google_marker_icon_picker/static/src/img/markers/blueviolet.png
odoo/addons/web_widget_google_marker_icon_picker/static/src/img/markers/brown.png
odoo/addons/web_widget_google_marker_icon_picker/static/src/img/markers/deepskyblue.png
odoo/addons/web_widget_google_marker_icon_picker/static/src/img/markers/fuchsia.png
odoo/addons/web_widget_google_marker_icon_picker/static/src/img/markers/gold.png
odoo/addons/web_widget_google_marker_icon_picker/static/src/img/markers/gray.png
odoo/addons/web_widget_google_marker_icon_picker/static/src/img/markers/green.png
odoo/addons/web_widget_google_marker_icon_picker/static/src/img/markers/indigo.png
odoo/addons/web_widget_google_marker_icon_picker/static/src/img/markers/lime.png
odoo/addons/web_widget_google_marker_icon_picker/static/src/img/markers/limegreen.png
odoo/addons/web_widget_google_marker_icon_picker/static/src/img/markers/maroon.png
odoo/addons/web_widget_google_marker_icon_picker/static/src/img/markers/navy.png
odoo/addons/web_widget_google_marker_icon_picker/static/src/img/markers/olive.png
odoo12_addon_web_widget_google_marker_icon_picker-12.0.1.1.0.99.dev2.dist-info/METADATA
odoo12_addon_web_widget_google_marker_icon_picker-12.0.1.1.0.99.dev2.dist-info/WHEEL
odoo12_addon_web_widget_google_marker_icon_picker-12.0.1.1.0.99.dev2.dist-info/top_level.txt
odoo12_addon_web_widget_google_marker_icon_picker-12.0.1.1.0.99.dev2.dist-info/RECORD
