Metadata-Version: 2.1
Name: odoo12-addon-web-widget-google-marker-icon-picker
Version: 12.0.1.1.0.99.dev2
Summary: Google map widget allowing to set marker's color
Home-page: https://github.com/OCA/geospatial
Author: Open Source Integrators, Odoo Community Association (OCA)
Author-email: support@odoo-community.org
License: AGPL-3
Platform: UNKNOWN
Classifier: Programming Language :: Python
Classifier: Framework :: Odoo
Classifier: Framework :: Odoo :: 12.0
Classifier: License :: OSI Approved :: GNU Affero General Public License v3
Requires-Python: >=3.5
Requires-Dist: odoo12-addon-web-view-google-map
Requires-Dist: odoo <12.1dev,>=12.0a
